{
  "title": "Урок 16: Диагностика системы и диска",
  "description": "Учимся быстро снимать системную сводку, смотреть память, файловые системы, usage по каталогам и искать тяжёлые файлы",
  "difficulty": "Intermediate",
  "time": "40",
  "details": {
    "intro": {
      "text": "intro.md"
    },
    "steps": [
      {
        "title": "Шаг 1: Быстрая сводка по системе",
        "text": "step1.md",
        "verify": "step1/verify.sh"
      },
      {
        "title": "Шаг 2: Проверяем память",
        "text": "step2.md",
        "verify": "step2/verify.sh"
      },
      {
        "title": "Шаг 3: Проверяем файловую систему",
        "text": "step3.md",
        "verify": "step3/verify.sh"
      },
      {
        "title": "Шаг 4: Смотрим usage по каталогам",
        "text": "step4.md",
        "verify": "step4/verify.sh"
      },
      {
        "title": "Шаг 5: Смотрим блоковые устройства и mount points",
        "text": "step5.md",
        "verify": "step5/verify.sh"
      },
      {
        "title": "Шаг 6: Ищем крупные файлы",
        "text": "step6.md",
        "verify": "step6/verify.sh"
      },
      {
        "title": "Шаг 7: Практика — находим самый тяжёлый артефакт",
        "text": "step7.md",
        "verify": "step7/verify.sh"
      }
    ],
    "finish": {
      "text": "finish.md"
    }
  },
  "backend": {
    "imageid": "ubuntu"
  }
}
